doge/__init__.py
doge/cluster/ha.py
doge/cluster/__init__.py
doge/cluster/endpoint.py
doge/cluster/lb.py
doge/config/config.py
doge/config/__init__.py
doge/common/doge.py
doge/common/__init__.py
doge/common/url.py
doge/common/utils.py
doge/common/exceptions.py
doge/registry/registry.py
doge/registry/__init__.py
doge/rpc/server.py
doge/rpc/client.py
doge/rpc/__init__.py
doge/rpc/context.py
dogerpc-0.1.4.dist-info/RECORD
dogerpc-0.1.4.dist-info/metadata.json
dogerpc-0.1.4.dist-info/WHEEL
dogerpc-0.1.4.dist-info/DESCRIPTION.rst
dogerpc-0.1.4.dist-info/top_level.txt
dogerpc-0.1.4.dist-info/METADATA
