Metadata-Version: 2.0
Name: dogerpc
Version: 0.1.4
Summary: A RPC Framework
Home-page: http://github.com/zhu327/doge
Author: Timmy
Author-email: zhu327@gmail.com
License: Apache License 2.0
Keywords: rpc,etcd,messagepack,gevent,microservices
Platform: UNKNOWN
Classifier: Development Status :: 4 - Beta
Classifier: Intended Audience :: Developers
Classifier: License :: OSI Approved :: Apache Software License
Classifier: Programming Language :: Python
Classifier: Programming Language :: Python :: 2.6
Classifier: Programming Language :: Python :: 2.7
Classifier: Programming Language :: Python :: 3.4
Classifier: Programming Language :: Python :: 3.5
Classifier: Programming Language :: Python :: 3.6
Requires-Dist: mprpc
Requires-Dist: pyformance
Requires-Dist: python-etcd
